fasthex/__init__.py
fasthex/fasthex.py
fasthex-0.0.1.dist-info/LICENSE.txt
fasthex-0.0.1.dist-info/METADATA
fasthex-0.0.1.dist-info/WHEEL
fasthex-0.0.1.dist-info/top_level.txt
fasthex-0.0.1.dist-info/RECORD
