Metadata-Version: 2.1
Name: fasthex
Version: 0.0.1
Summary: A fast python 3 implemenation of Intel Hex Format
Home-page: https://github.com/menschel/fasthex
Author: Patrick Menschel
Author-email: menschel.p@posteo.de
License: UNKNOWN
Keywords: Intel HEX
Platform: UNKNOWN
Classifier: Development Status :: 5 - Production/Stable
Classifier: Programming Language :: Python :: 3
Classifier: License :: OSI Approved :: GNU General Public License v3 or later (GPLv3+)
Classifier: Operating System :: OS Independent
Classifier: Intended Audience :: Science/Research
Classifier: Intended Audience :: Developers
Classifier: Topic :: Scientific/Engineering
Classifier: Topic :: Software Development :: Embedded Systems
Classifier: Topic :: Utilities
Requires-Python: >=3.6
